setup.py
cypico/__init__.py
cypico/pico.cpp
cypico/pico.pxd
cypico/pico.pyx
cypico/pico_wrapper.cpp
cypico/pico_wrapper.h
cypico.egg-info/PKG-INFO
cypico.egg-info/SOURCES.txt
cypico.egg-info/dependency_links.txt
cypico.egg-info/requires.txt
cypico.egg-info/top_level.txt
cypico/pico/runtime/picort.cpp
cypico/pico/runtime/picort.h
cypico/pico/runtime/cascades/facefinder.ea