Metadata-Version: 1.0
Name: cypico
Version: 0.2.2
Summary: A Cython wrapper around the Pico face detection library.
Home-page: https://github.com/menpo/cypico
Author: Patrick Snape
Author-email: p.snape@imperial.ac.uk
License: UNKNOWN
Platform: UNKNOWN
